omero/plugins/duplicate.py
omero_cli_duplicate-0.4.0.dist-info/LICENSE.txt
omero_cli_duplicate-0.4.0.dist-info/METADATA
omero_cli_duplicate-0.4.0.dist-info/WHEEL
omero_cli_duplicate-0.4.0.dist-info/top_level.txt
omero_cli_duplicate-0.4.0.dist-info/RECORD
